pytelpoint/__init__.py
pytelpoint/_astropy_init.py
pytelpoint/conftest.py
pytelpoint/constants.py
pytelpoint/fitting.py
pytelpoint/io.py
pytelpoint/stats.py
pytelpoint/transform.py
pytelpoint/version.py
pytelpoint/visualization.py
pytelpoint/extern/__init__.py
pytelpoint/test_data/k_and_e.dat
pytelpoint/test_data/point_20210821.dat
pytelpoint/tests/__init__.py
pytelpoint/tests/test_fitting.py
pytelpoint/tests/test_io.py
pytelpoint/tests/test_stats.py
pytelpoint/tests/test_transform.py
pytelpoint/tests/test_viz.py
pytelpoint/utils/__init__.py
pytelpoint/utils/tests/__init__.py
pytelpoint-1.0.0.dist-info/LICENSE.rst
pytelpoint-1.0.0.dist-info/METADATA
pytelpoint-1.0.0.dist-info/WHEEL
pytelpoint-1.0.0.dist-info/top_level.txt
pytelpoint-1.0.0.dist-info/RECORD
