Metadata-Version: 2.1
Name: pytelpoint
Version: 1.0.0
Summary: Python utilities for analyzing telescope pointing and tracking via probabilistic methods
Home-page: https://github.com/mmtobservatory/pytelpoint
Author: T. E. Pickering
Author-email: te.pickering@gmail.com
License: BSD 3-Clause
Requires-Python: >=3.8
License-File: licenses/LICENSE.rst
Requires-Dist: scipy
Requires-Dist: astropy
Requires-Dist: matplotlib
Requires-Dist: arviz
Requires-Dist: corner
Requires-Dist: pymc
Requires-Dist: pandas
Provides-Extra: dev
Requires-Dist: ipympl ; extra == 'dev'
Provides-Extra: docs
Requires-Dist: sphinx-astropy ; extra == 'docs'
Provides-Extra: test
Requires-Dist: tox ; extra == 'test'
Requires-Dist: pytest-astropy ; extra == 'test'
